Metadata-Version: 2.1
Name: django-simple-captcha-audio-espeak
Version: 0.5.13
Summary: A very simple, yet powerful, Django captcha application with eSpeak support
Home-page: https://github.com/krystofbe/
Author: Marco Bonetti, Krystof Beuermann
Author-email: mbonetti@gmail.com, krystof@blackbox.ms
License: MIT
Platform: UNKNOWN
Classifier: Development Status :: 4 - Beta
Classifier: Environment :: Web Environment
Classifier: Intended Audience :: Developers
Classifier: License :: OSI Approved :: MIT License
Classifier: Operating System :: OS Independent
Classifier: Programming Language :: Python
Classifier: Programming Language :: Python :: 2.7
Classifier: Programming Language :: Python :: 3.4
Classifier: Programming Language :: Python :: 3.5
Classifier: Programming Language :: Python :: 3.6
Classifier: Topic :: Security
Classifier: Topic :: Internet :: WWW/HTTP
Classifier: Framework :: Django
Provides-Extra: test
